{
  "openapi": "3.0.0",
  "info": {
    "version": "1.0.0",
    "title": "node-ts-boilerplate",
    "description": "node typescript document",
    "license": {
      "name": "MIT",
      "url": "https://opensource.org/licenses/MIT"
    }
  },
  "servers": [
    {"url": "http://localhost:8080/api", "description": "base URL"}
  ],
  "tags": [
    {
      "name": "User",
      "description": "User Account"
    },
    {
      "name": "Task",
      "description": "Task of user"
    }
  ],
  "paths": {
    "/users": {
      "post": {
        "tags": ["User"],
        "requestBody": {
          "content": {
            "application/json": {
              "schema": {
                "$ref": "#/components/schemas/User"
              }
            }
          }
        },
        "responses": {
          "200": {
            "description": "success",
            "content": {
              "application/json": {
                "schema": {
                  "$ref": "#/components/schemas/User"
                }
              }
            }
          }
        }
      },
      "get": {
        "tags": ["User"],
        "responses": {
          "200": {
            "description": "success",
            "content": {
              "application/json": {
                "schema": {
                  "type": "array",
                  "items": {
                    "$ref": "#/components/schemas/User"
                  }
                }
              }
            }
          }
        }
      }
    }
  },
  "components": {
    "schemas": {
      "User": {
        "type": "object",
        "properties": {
          "id": {
            "type": "string"
          },
          "email": {
            "type": "string",
            "format": "email"
          },
          "username": {
            "type": "string"
          },
          "password": {
            "type": "string"
          },
          "createdAt": {
            "type": "string",
            "format": "date-time"
          },
          "updatedAt": {
            "type": "string",
            "format": "date-time"
          }
        }
      },
      "Task": {
        "type": "object",
        "properties": {
          "id": {
            "type": "string"
          },
          "detail": {
            "type": "string"
          }
        }
      }
    },
    "securitySchemes": {
      "auth": {
        "type": "http",
        "scheme": "bearer"
      }
    }
  }
}